flitz/__init__.py
flitz/__main__.py
flitz/_version.py
flitz/cli.py
flitz/config.py
flitz/context_menu.py
flitz/file_explorer.py
flitz/file_properties_dialog.py
flitz/icon.gif
flitz/ui_utils.py
flitz/utils.py
flitz/static/file.jpg
flitz/static/folder.jpg
flitz/static/up.png
flitz-0.0.6.dist-info/entry_points.txt
flitz-0.0.6.dist-info/LICENSE
flitz-0.0.6.dist-info/WHEEL
flitz-0.0.6.dist-info/METADATA
flitz-0.0.6.dist-info/RECORD
